rastertodataframe/__init__.py
rastertodataframe/rastertodataframe.py
rastertodataframe/tiling.py
rastertodataframe/util.py
rastertodataframe-0.2.1.dist-info/METADATA
rastertodataframe-0.2.1.dist-info/RECORD
rastertodataframe-0.2.1.dist-info/WHEEL
rastertodataframe-0.2.1.dist-info/top_level.txt
