Metadata-Version: 2.1
Name: rastertodataframe
Version: 0.2.1
Summary: A simple python module that converts a raster to a Pandas DataFrame.
Home-page: https://github.com/mblack20/rastertodataframe
Author: Martin Black
Author-email: mblack@posteo.de
License: MIT license
Keywords: rastertodataframe
Platform: UNKNOWN
Classifier: Development Status :: 2 - Pre-Alpha
Classifier: Intended Audience :: Developers
Classifier: License :: OSI Approved :: MIT License
Classifier: Natural Language :: English
Classifier: Programming Language :: Python :: 3
Classifier: Programming Language :: Python :: 3.4
Classifier: Programming Language :: Python :: 3.5
Classifier: Programming Language :: Python :: 3.6
